{"children": [{"name": "レイヤー 1", "visible": true, "path": "レイヤー 1", "left": 0, "top": 0, "width": 640, "height": 480}, {"name": "レイヤー 2", "visible": true, "path": "レイヤー 2", "left": 0, "top": 0, "width": 640, "height": 480}, {"name": "レイヤー 3", "visible": true, "path": "レイヤー 3", "left": 0, "top": 0, "width": 640, "height": 480}, {"name": "レイヤー 4", "visible": true, "path": "レイヤー 4", "left": 0, "top": 0, "width": 642, "height": 480}, {"name": "レイヤー 5", "visible": true, "path": "レイヤー 5", "left": 0, "top": 0, "width": 642, "height": 480}, {"name": "レイヤー 6", "visible": true, "path": "レイヤー 6", "left": 0, "top": 0, "width": 642, "height": 480}, {"name": "レイヤー 7", "visible": true, "path": "レイヤー 7", "left": 0, "top": 0, "width": 642, "height": 484}, {"name": "レイヤー 8", "visible": true, "path": "レイヤー 8", "left": 0, "top": 0, "width": 642, "height": 480}, {"name": "レイヤー 9", "visible": true, "path": "レイヤー 9", "left": 0, "top": 0, "width": 642, "height": 480}, {"name": "レイヤー 10", "visible": true, "path": "レイヤー 10", "left": 0, "top": 0, "width": 642, "height": 480}, {"name": "レイヤー 11", "visible": true, "path": "レイヤー 11", "left": 0, "top": 0, "width": 642, "height": 480}, {"name": "レイヤー 12", "visible": true, "path": "レイヤー 12", "left": 0, "top": 0, "width": 642, "height": 480}, {"name": "レイヤー 13", "visible": true, "path": "レイヤー 13", "left": 0, "top": 0, "width": 642, "height": 480}, {"name": "レイヤー 14", "visible": true, "opacity": 0.8, "path": "レイヤー 14", "left": 0, "top": 0, "width": 642, "height": 480}, {"name": "レイヤー 15", "visible": true, "opacity": 0.6, "path": "レイヤー 15", "left": 0, "top": 0, "width": 642, "height": 480}, {"name": "レイヤー 16", "visible": true, "opacity": 0.4, "path": "レイヤー 16", "left": 0, "top": 0, "width": 641, "height": 480}, {"name": "レイヤー 17", "visible": true, "opacity": 0.2, "path": "レイヤー 17", "left": 0, "top": 0, "width": 640, "height": 480}]}