{"children": [{"name": "sky", "visible": true, "path": "sky", "left": 0, "top": 0, "width": 640, "height": 480}, {"name": "MØÀü", "visible": true, "path": "MØÀü", "left": 1, "top": 7, "width": 644, "height": 483}, {"name": "shade", "visible": true, "opacity": 0.7019607843137254, "path": "shade", "left": 0, "top": 21, "width": 479, "height": 391}, {"name": "page4", "visible": true, "path": "page4", "left": 139, "top": 16, "width": 336, "height": 391}, {"name": "page3", "visible": true, "path": "page3", "left": 139, "top": 16, "width": 336, "height": 391}, {"name": "page2", "visible": true, "path": "page2", "left": 139, "top": 16, "width": 336, "height": 391}, {"name": "page1", "visible": true, "path": "page1", "left": 139, "top": 16, "width": 336, "height": 391}, {"name": "load", "visible": true, "path": "load", "left": -4, "top": 210, "width": 151, "height": 108}, {"name": "save", "visible": true, "path": "save", "left": -4, "top": 210, "width": 151, "height": 108}]}