{"children": [{"name": "照れ２", "visible": true, "path": "照れ２", "left": 108, "top": 59, "width": 402, "height": 421}, {"name": "照れ", "visible": true, "path": "照れ", "left": 190, "top": 60, "width": 280, "height": 420}, {"name": "微笑み", "visible": true, "path": "微笑み", "left": 96, "top": 64, "width": 412, "height": 416}, {"name": "ご機嫌", "visible": true, "path": "ご機嫌", "left": 101, "top": 61, "width": 332, "height": 419}, {"name": "虚ろ", "visible": true, "path": "虚ろ", "left": 203, "top": 59, "width": 252, "height": 421}, {"name": "疑問", "visible": true, "path": "疑問", "left": 176, "top": 67, "width": 277, "height": 413}, {"name": "驚き２", "visible": true, "path": "驚き２", "left": 110, "top": 60, "width": 462, "height": 420}, {"name": "驚き", "visible": true, "path": "驚き", "left": 181, "top": 65, "width": 271, "height": 415}, {"name": "哀", "visible": true, "path": "哀", "left": 178, "top": 65, "width": 259, "height": 415}, {"name": "怒", "visible": true, "path": "怒", "left": 158, "top": 63, "width": 351, "height": 417}, {"name": "喜", "visible": true, "path": "喜", "left": 171, "top": 58, "width": 263, "height": 422}, {"name": "通常２", "visible": true, "path": "通常２", "left": 191, "top": 66, "width": 250, "height": 414}, {"name": "通常", "visible": true, "path": "通常", "left": 167, "top": 62, "width": 323, "height": 418}]}